graphql_ws/__init__.py
graphql_ws/abc.py
graphql_ws/aiohttp.py
graphql_ws/protocol.py
graphql_ws/server.py
graphql_ws/testing.py
graphql_ws_next-1.0.0.dist-info/LICENSE
graphql_ws_next-1.0.0.dist-info/WHEEL
graphql_ws_next-1.0.0.dist-info/METADATA
graphql_ws_next-1.0.0.dist-info/RECORD
